<?xml version="1.0" encoding="utf-8"?><annotation> <filename>05584a52-730a88df.jpg</filename> <object>  <name>traffic sign</name>  <bndbox>   <xmin>593</xmin>   <ymin>0</ymin>   <xmax>652</xmax>   <ymax>37</ymax>  </bndbox> </object> <object>  <name>traffic sign</name>  <bndbox>   <xmin>836</xmin>   <ymin>227</ymin>   <xmax>889</xmax>   <ymax>264</ymax>  </bndbox> </object> <object>  <name>traffic sign</name>  <bndbox>   <xmin>750</xmin>   <ymin>153</ymin>   <xmax>778</xmax>   <ymax>193</ymax>  </bndbox> </object> <object>  <name>traffic sign</name>  <bndbox>   <xmin>800</xmin>   <ymin>248</ymin>   <xmax>814</xmax>   <ymax>263</ymax>  </bndbox> </object> <object>  <name>car</name>  <bndbox>   <xmin>205</xmin>   <ymin>277</ymin>   <xmax>231</xmax>   <ymax>296</ymax>  </bndbox> </object> <object>  <name>car</name>  <bndbox>   <xmin>539</xmin>   <ymin>289</ymin>   <xmax>558</xmax>   <ymax>306</ymax>  </bndbox> </object> <object>  <name>car</name>  <bndbox>   <xmin>466</xmin>   <ymin>289</ymin>   <xmax>515</xmax>   <ymax>308</ymax>  </bndbox> </object> <object>  <name>car</name>  <bndbox>   <xmin>135</xmin>   <ymin>264</ymin>   <xmax>202</xmax>   <ymax>304</ymax>  </bndbox> </object> <object>  <name>traffic light</name>  <bndbox>   <xmin>804</xmin>   <ymin>271</ymin>   <xmax>815</xmax>   <ymax>280</ymax>  </bndbox> </object> <object>  <name>traffic light</name>  <bndbox>   <xmin>689</xmin>   <ymin>286</ymin>   <xmax>701</xmax>   <ymax>294</ymax>  </bndbox> </object> <object>  <name>traffic light</name>  <bndbox>   <xmin>571</xmin>   <ymin>277</ymin>   <xmax>582</xmax>   <ymax>287</ymax>  </bndbox> </object> <object>  <name>traffic sign</name>  <bndbox>   <xmin>380</xmin>   <ymin>228</ymin>   <xmax>406</xmax>   <ymax>258</ymax>  </bndbox> </object></annotation>