<?xml version="1.0" encoding="utf-8"?><annotation> <filename>148e0e5c-fdaacba4.jpg</filename> <object>  <name>traffic light</name>  <bndbox>   <xmin>622</xmin>   <ymin>71</ymin>   <xmax>634</xmax>   <ymax>103</ymax>  </bndbox> </object> <object>  <name>traffic light</name>  <bndbox>   <xmin>297</xmin>   <ymin>177</ymin>   <xmax>315</xmax>   <ymax>194</ymax>  </bndbox> </object> <object>  <name>traffic light</name>  <bndbox>   <xmin>1225</xmin>   <ymin>90</ymin>   <xmax>1244</xmax>   <ymax>119</ymax>  </bndbox> </object> <object>  <name>traffic light</name>  <bndbox>   <xmin>1188</xmin>   <ymin>102</ymin>   <xmax>1209</xmax>   <ymax>142</ymax>  </bndbox> </object> <object>  <name>traffic light</name>  <bndbox>   <xmin>602</xmin>   <ymin>215</ymin>   <xmax>612</xmax>   <ymax>230</ymax>  </bndbox> </object> <object>  <name>traffic sign</name>  <bndbox>   <xmin>574</xmin>   <ymin>220</ymin>   <xmax>594</xmax>   <ymax>227</ymax>  </bndbox> </object> <object>  <name>traffic sign</name>  <bndbox>   <xmin>459</xmin>   <ymin>89</ymin>   <xmax>541</xmax>   <ymax>113</ymax>  </bndbox> </object> <object>  <name>traffic sign</name>  <bndbox>   <xmin>320</xmin>   <ymin>59</ymin>   <xmax>346</xmax>   <ymax>104</ymax>  </bndbox> </object> <object>  <name>traffic sign</name>  <bndbox>   <xmin>313</xmin>   <ymin>126</ymin>   <xmax>340</xmax>   <ymax>140</ymax>  </bndbox> </object> <object>  <name>pedestrian</name>  <bndbox>   <xmin>602</xmin>   <ymin>243</ymin>   <xmax>618</xmax>   <ymax>296</ymax>  </bndbox> </object> <object>  <name>truck</name>  <bndbox>   <xmin>944</xmin>   <ymin>282</ymin>   <xmax>1009</xmax>   <ymax>328</ymax>  </bndbox> </object> <object>  <name>car</name>  <bndbox>   <xmin>987</xmin>   <ymin>296</ymin>   <xmax>1065</xmax>   <ymax>340</ymax>  </bndbox> </object> <object>  <name>car</name>  <bndbox>   <xmin>629</xmin>   <ymin>179</ymin>   <xmax>945</xmax>   <ymax>351</ymax>  </bndbox> </object> <object>  <name>car</name>  <bndbox>   <xmin>512</xmin>   <ymin>264</ymin>   <xmax>528</xmax>   <ymax>290</ymax>  </bndbox> </object> <object>  <name>car</name>  <bndbox>   <xmin>427</xmin>   <ymin>248</ymin>   <xmax>519</xmax>   <ymax>309</ymax>  </bndbox> </object> <object>  <name>pedestrian</name>  <bndbox>   <xmin>310</xmin>   <ymin>229</ymin>   <xmax>335</xmax>   <ymax>306</ymax>  </bndbox> </object> <object>  <name>car</name>  <bndbox>   <xmin>509</xmin>   <ymin>248</ymin>   <xmax>557</xmax>   <ymax>286</ymax>  </bndbox> </object> <object>  <name>car</name>  <bndbox>   <xmin>552</xmin>   <ymin>257</ymin>   <xmax>574</xmax>   <ymax>281</ymax>  </bndbox> </object> <object>  <name>car</name>  <bndbox>   <xmin>567</xmin>   <ymin>261</ymin>   <xmax>585</xmax>   <ymax>281</ymax>  </bndbox> </object> <object>  <name>traffic sign</name>  <bndbox>   <xmin>1246</xmin>   <ymin>123</ymin>   <xmax>1277</xmax>   <ymax>147</ymax>  </bndbox> </object></annotation>