<?xml version="1.0" encoding="utf-8"?><annotation> <filename>2ad1aa4b-296d52e4.jpg</filename> <object>  <name>car</name>  <bndbox>   <xmin>490</xmin>   <ymin>298</ymin>   <xmax>542</xmax>   <ymax>345</ymax>  </bndbox> </object> <object>  <name>car</name>  <bndbox>   <xmin>578</xmin>   <ymin>295</ymin>   <xmax>640</xmax>   <ymax>342</ymax>  </bndbox> </object> <object>  <name>car</name>  <bndbox>   <xmin>565</xmin>   <ymin>308</ymin>   <xmax>579</xmax>   <ymax>323</ymax>  </bndbox> </object> <object>  <name>car</name>  <bndbox>   <xmin>538</xmin>   <ymin>305</ymin>   <xmax>559</xmax>   <ymax>321</ymax>  </bndbox> </object></annotation>