<?xml version="1.0" encoding="utf-8"?><annotation> <filename>2e1a2a13-3304f78d.jpg</filename> <object>  <name>car</name>  <bndbox>   <xmin>346</xmin>   <ymin>255</ymin>   <xmax>514</xmax>   <ymax>328</ymax>  </bndbox> </object> <object>  <name>car</name>  <bndbox>   <xmin>213</xmin>   <ymin>269</ymin>   <xmax>363</xmax>   <ymax>306</ymax>  </bndbox> </object> <object>  <name>car</name>  <bndbox>   <xmin>245</xmin>   <ymin>274</ymin>   <xmax>487</xmax>   <ymax>367</ymax>  </bndbox> </object> <object>  <name>car</name>  <bndbox>   <xmin>8</xmin>   <ymin>261</ymin>   <xmax>276</xmax>   <ymax>374</ymax>  </bndbox> </object> <object>  <name>car</name>  <bndbox>   <xmin>0</xmin>   <ymin>279</ymin>   <xmax>50</xmax>   <ymax>393</ymax>  </bndbox> </object></annotation>