<?xml version="1.0" encoding="utf-8"?><annotation> <filename>3459fa44-b719ce57.jpg</filename> <object>  <name>traffic sign</name>  <bndbox>   <xmin>1112</xmin>   <ymin>56</ymin>   <xmax>1170</xmax>   <ymax>162</ymax>  </bndbox> </object> <object>  <name>car</name>  <bndbox>   <xmin>1005</xmin>   <ymin>263</ymin>   <xmax>1135</xmax>   <ymax>331</ymax>  </bndbox> </object> <object>  <name>car</name>  <bndbox>   <xmin>731</xmin>   <ymin>296</ymin>   <xmax>865</xmax>   <ymax>366</ymax>  </bndbox> </object> <object>  <name>traffic light</name>  <bndbox>   <xmin>615</xmin>   <ymin>289</ymin>   <xmax>626</xmax>   <ymax>300</ymax>  </bndbox> </object> <object>  <name>traffic light</name>  <bndbox>   <xmin>561</xmin>   <ymin>274</ymin>   <xmax>576</xmax>   <ymax>286</ymax>  </bndbox> </object> <object>  <name>car</name>  <bndbox>   <xmin>544</xmin>   <ymin>306</ymin>   <xmax>557</xmax>   <ymax>323</ymax>  </bndbox> </object> <object>  <name>car</name>  <bndbox>   <xmin>465</xmin>   <ymin>304</ymin>   <xmax>489</xmax>   <ymax>328</ymax>  </bndbox> </object> <object>  <name>car</name>  <bndbox>   <xmin>426</xmin>   <ymin>303</ymin>   <xmax>466</xmax>   <ymax>336</ymax>  </bndbox> </object> <object>  <name>car</name>  <bndbox>   <xmin>393</xmin>   <ymin>311</ymin>   <xmax>429</xmax>   <ymax>345</ymax>  </bndbox> </object> <object>  <name>car</name>  <bndbox>   <xmin>334</xmin>   <ymin>321</ymin>   <xmax>383</xmax>   <ymax>364</ymax>  </bndbox> </object> <object>  <name>car</name>  <bndbox>   <xmin>281</xmin>   <ymin>321</ymin>   <xmax>341</xmax>   <ymax>375</ymax>  </bndbox> </object> <object>  <name>traffic light</name>  <bndbox>   <xmin>518</xmin>   <ymin>289</ymin>   <xmax>525</xmax>   <ymax>306</ymax>  </bndbox> </object></annotation>