<?xml version="1.0" encoding="utf-8"?><annotation> <filename>3d46ebc7-43221184.jpg</filename> <object>  <name>car</name>  <bndbox>   <xmin>422</xmin>   <ymin>348</ymin>   <xmax>787</xmax>   <ymax>571</ymax>  </bndbox> </object> <object>  <name>car</name>  <bndbox>   <xmin>267</xmin>   <ymin>388</ymin>   <xmax>370</xmax>   <ymax>473</ymax>  </bndbox> </object> <object>  <name>car</name>  <bndbox>   <xmin>149</xmin>   <ymin>415</ymin>   <xmax>205</xmax>   <ymax>457</ymax>  </bndbox> </object> <object>  <name>car</name>  <bndbox>   <xmin>213</xmin>   <ymin>421</ymin>   <xmax>235</xmax>   <ymax>440</ymax>  </bndbox> </object></annotation>