<?xml version="1.0" encoding="utf-8"?><annotation> <filename>3f8db209-f82fd95a.jpg</filename> <object>  <name>car</name>  <bndbox>   <xmin>525</xmin>   <ymin>351</ymin>   <xmax>591</xmax>   <ymax>409</ymax>  </bndbox> </object> <object>  <name>car</name>  <bndbox>   <xmin>422</xmin>   <ymin>357</ymin>   <xmax>486</xmax>   <ymax>404</ymax>  </bndbox> </object> <object>  <name>traffic sign</name>  <bndbox>   <xmin>723</xmin>   <ymin>341</ymin>   <xmax>733</xmax>   <ymax>354</ymax>  </bndbox> </object> <object>  <name>traffic sign</name>  <bndbox>   <xmin>612</xmin>   <ymin>341</ymin>   <xmax>621</xmax>   <ymax>354</ymax>  </bndbox> </object> <object>  <name>traffic sign</name>  <bndbox>   <xmin>1184</xmin>   <ymin>218</ymin>   <xmax>1216</xmax>   <ymax>270</ymax>  </bndbox> </object> <object>  <name>traffic light</name>  <bndbox>   <xmin>1194</xmin>   <ymin>95</ymin>   <xmax>1211</xmax>   <ymax>120</ymax>  </bndbox> </object></annotation>