<?xml version="1.0" encoding="utf-8"?><annotation> <filename>4046a0a6-be9f846d.jpg</filename> <object>  <name>car</name>  <bndbox>   <xmin>5</xmin>   <ymin>370</ymin>   <xmax>50</xmax>   <ymax>447</ymax>  </bndbox> </object> <object>  <name>car</name>  <bndbox>   <xmin>95</xmin>   <ymin>289</ymin>   <xmax>505</xmax>   <ymax>598</ymax>  </bndbox> </object> <object>  <name>car</name>  <bndbox>   <xmin>16</xmin>   <ymin>335</ymin>   <xmax>158</xmax>   <ymax>421</ymax>  </bndbox> </object> <object>  <name>car</name>  <bndbox>   <xmin>140</xmin>   <ymin>332</ymin>   <xmax>178</xmax>   <ymax>363</ymax>  </bndbox> </object> <object>  <name>car</name>  <bndbox>   <xmin>439</xmin>   <ymin>323</ymin>   <xmax>470</xmax>   <ymax>357</ymax>  </bndbox> </object> <object>  <name>traffic light</name>  <bndbox>   <xmin>407</xmin>   <ymin>297</ymin>   <xmax>417</xmax>   <ymax>311</ymax>  </bndbox> </object> <object>  <name>traffic sign</name>  <bndbox>   <xmin>441</xmin>   <ymin>293</ymin>   <xmax>460</xmax>   <ymax>304</ymax>  </bndbox> </object> <object>  <name>traffic sign</name>  <bndbox>   <xmin>110</xmin>   <ymin>276</ymin>   <xmax>131</xmax>   <ymax>303</ymax>  </bndbox> </object></annotation>