<?xml version="1.0" encoding="utf-8"?><annotation> <filename>483bee0e-1704c08b.jpg</filename> <object>  <name>bicycle</name>  <bndbox>   <xmin>14</xmin>   <ymin>217</ymin>   <xmax>106</xmax>   <ymax>321</ymax>  </bndbox> </object> <object>  <name>rider</name>  <bndbox>   <xmin>26</xmin>   <ymin>172</ymin>   <xmax>100</xmax>   <ymax>302</ymax>  </bndbox> </object> <object>  <name>traffic light</name>  <bndbox>   <xmin>957</xmin>   <ymin>145</ymin>   <xmax>988</xmax>   <ymax>176</ymax>  </bndbox> </object> <object>  <name>traffic sign</name>  <bndbox>   <xmin>991</xmin>   <ymin>113</ymin>   <xmax>1044</xmax>   <ymax>136</ymax>  </bndbox> </object> <object>  <name>truck</name>  <bndbox>   <xmin>579</xmin>   <ymin>244</ymin>   <xmax>597</xmax>   <ymax>275</ymax>  </bndbox> </object> <object>  <name>car</name>  <bndbox>   <xmin>567</xmin>   <ymin>257</ymin>   <xmax>583</xmax>   <ymax>278</ymax>  </bndbox> </object> <object>  <name>truck</name>  <bndbox>   <xmin>526</xmin>   <ymin>236</ymin>   <xmax>571</xmax>   <ymax>277</ymax>  </bndbox> </object> <object>  <name>pedestrian</name>  <bndbox>   <xmin>459</xmin>   <ymin>239</ymin>   <xmax>475</xmax>   <ymax>277</ymax>  </bndbox> </object> <object>  <name>truck</name>  <bndbox>   <xmin>128</xmin>   <ymin>107</ymin>   <xmax>450</xmax>   <ymax>359</ymax>  </bndbox> </object> <object>  <name>car</name>  <bndbox>   <xmin>588</xmin>   <ymin>223</ymin>   <xmax>685</xmax>   <ymax>302</ymax>  </bndbox> </object> <object>  <name>car</name>  <bndbox>   <xmin>1060</xmin>   <ymin>264</ymin>   <xmax>1151</xmax>   <ymax>326</ymax>  </bndbox> </object></annotation>