<?xml version="1.0" encoding="utf-8"?><annotation> <filename>58610009-3fa4ebe7.jpg</filename> <object>  <name>traffic light</name>  <bndbox>   <xmin>293</xmin>   <ymin>316</ymin>   <xmax>305</xmax>   <ymax>329</ymax>  </bndbox> </object> <object>  <name>traffic light</name>  <bndbox>   <xmin>514</xmin>   <ymin>318</ymin>   <xmax>529</xmax>   <ymax>333</ymax>  </bndbox> </object> <object>  <name>traffic light</name>  <bndbox>   <xmin>634</xmin>   <ymin>361</ymin>   <xmax>651</xmax>   <ymax>379</ymax>  </bndbox> </object> <object>  <name>traffic sign</name>  <bndbox>   <xmin>624</xmin>   <ymin>337</ymin>   <xmax>643</xmax>   <ymax>348</ymax>  </bndbox> </object> <object>  <name>traffic sign</name>  <bndbox>   <xmin>627</xmin>   <ymin>323</ymin>   <xmax>647</xmax>   <ymax>334</ymax>  </bndbox> </object> <object>  <name>car</name>  <bndbox>   <xmin>462</xmin>   <ymin>388</ymin>   <xmax>484</xmax>   <ymax>412</ymax>  </bndbox> </object> <object>  <name>car</name>  <bndbox>   <xmin>430</xmin>   <ymin>390</ymin>   <xmax>460</xmax>   <ymax>413</ymax>  </bndbox> </object> <object>  <name>car</name>  <bndbox>   <xmin>477</xmin>   <ymin>388</ymin>   <xmax>527</xmax>   <ymax>429</ymax>  </bndbox> </object> <object>  <name>car</name>  <bndbox>   <xmin>269</xmin>   <ymin>397</ymin>   <xmax>361</xmax>   <ymax>449</ymax>  </bndbox> </object> <object>  <name>car</name>  <bndbox>   <xmin>0</xmin>   <ymin>412</ymin>   <xmax>57</xmax>   <ymax>511</ymax>  </bndbox> </object> <object>  <name>traffic sign</name>  <bndbox>   <xmin>1147</xmin>   <ymin>2</ymin>   <xmax>1260</xmax>   <ymax>87</ymax>  </bndbox> </object> <object>  <name>car</name>  <bndbox>   <xmin>766</xmin>   <ymin>387</ymin>   <xmax>870</xmax>   <ymax>430</ymax>  </bndbox> </object> <object>  <name>car</name>  <bndbox>   <xmin>544</xmin>   <ymin>390</ymin>   <xmax>566</xmax>   <ymax>408</ymax>  </bndbox> </object></annotation>