<?xml version="1.0" encoding="utf-8"?><annotation> <filename>5fbe59b9-5acdc451.jpg</filename> <object>  <name>car</name>  <bndbox>   <xmin>581</xmin>   <ymin>335</ymin>   <xmax>597</xmax>   <ymax>352</ymax>  </bndbox> </object> <object>  <name>car</name>  <bndbox>   <xmin>568</xmin>   <ymin>345</ymin>   <xmax>579</xmax>   <ymax>366</ymax>  </bndbox> </object> <object>  <name>truck</name>  <bndbox>   <xmin>499</xmin>   <ymin>286</ymin>   <xmax>569</xmax>   <ymax>384</ymax>  </bndbox> </object> <object>  <name>traffic sign</name>  <bndbox>   <xmin>536</xmin>   <ymin>247</ymin>   <xmax>653</xmax>   <ymax>301</ymax>  </bndbox> </object> <object>  <name>traffic sign</name>  <bndbox>   <xmin>478</xmin>   <ymin>265</ymin>   <xmax>502</xmax>   <ymax>298</ymax>  </bndbox> </object> <object>  <name>traffic sign</name>  <bndbox>   <xmin>677</xmin>   <ymin>314</ymin>   <xmax>701</xmax>   <ymax>337</ymax>  </bndbox> </object></annotation>