<?xml version="1.0" encoding="utf-8"?><annotation> <filename>6b0cb404-f9b82803.jpg</filename> <object>  <name>traffic sign</name>  <bndbox>   <xmin>916</xmin>   <ymin>70</ymin>   <xmax>995</xmax>   <ymax>120</ymax>  </bndbox> </object> <object>  <name>traffic sign</name>  <bndbox>   <xmin>934</xmin>   <ymin>119</ymin>   <xmax>979</xmax>   <ymax>160</ymax>  </bndbox> </object> <object>  <name>traffic sign</name>  <bndbox>   <xmin>937</xmin>   <ymin>157</ymin>   <xmax>979</xmax>   <ymax>178</ymax>  </bndbox> </object> <object>  <name>traffic sign</name>  <bndbox>   <xmin>947</xmin>   <ymin>178</ymin>   <xmax>979</xmax>   <ymax>245</ymax>  </bndbox> </object> <object>  <name>car</name>  <bndbox>   <xmin>145</xmin>   <ymin>287</ymin>   <xmax>285</xmax>   <ymax>450</ymax>  </bndbox> </object> <object>  <name>car</name>  <bndbox>   <xmin>0</xmin>   <ymin>368</ymin>   <xmax>142</xmax>   <ymax>555</ymax>  </bndbox> </object> <object>  <name>car</name>  <bndbox>   <xmin>228</xmin>   <ymin>179</ymin>   <xmax>836</xmax>   <ymax>634</ymax>  </bndbox> </object> <object>  <name>car</name>  <bndbox>   <xmin>819</xmin>   <ymin>197</ymin>   <xmax>1277</xmax>   <ymax>632</ymax>  </bndbox> </object> <object>  <name>car</name>  <bndbox>   <xmin>76</xmin>   <ymin>292</ymin>   <xmax>150</xmax>   <ymax>350</ymax>  </bndbox> </object> <object>  <name>car</name>  <bndbox>   <xmin>771</xmin>   <ymin>278</ymin>   <xmax>884</xmax>   <ymax>371</ymax>  </bndbox> </object></annotation>