<?xml version="1.0" encoding="utf-8"?><annotation> <filename>70c68f3b-81cfdf2e.jpg</filename> <object>  <name>traffic sign</name>  <bndbox>   <xmin>590</xmin>   <ymin>396</ymin>   <xmax>598</xmax>   <ymax>406</ymax>  </bndbox> </object> <object>  <name>traffic sign</name>  <bndbox>   <xmin>633</xmin>   <ymin>333</ymin>   <xmax>669</xmax>   <ymax>368</ymax>  </bndbox> </object> <object>  <name>car</name>  <bndbox>   <xmin>458</xmin>   <ymin>374</ymin>   <xmax>503</xmax>   <ymax>411</ymax>  </bndbox> </object> <object>  <name>traffic sign</name>  <bndbox>   <xmin>40</xmin>   <ymin>313</ymin>   <xmax>82</xmax>   <ymax>365</ymax>  </bndbox> </object></annotation>