<?xml version="1.0" encoding="utf-8"?><annotation> <filename>774372bd-64180da0.jpg</filename> <object>  <name>car</name>  <bndbox>   <xmin>9</xmin>   <ymin>288</ymin>   <xmax>78</xmax>   <ymax>324</ymax>  </bndbox> </object> <object>  <name>car</name>  <bndbox>   <xmin>89</xmin>   <ymin>297</ymin>   <xmax>118</xmax>   <ymax>320</ymax>  </bndbox> </object> <object>  <name>car</name>  <bndbox>   <xmin>110</xmin>   <ymin>293</ymin>   <xmax>150</xmax>   <ymax>320</ymax>  </bndbox> </object> <object>  <name>truck</name>  <bndbox>   <xmin>202</xmin>   <ymin>262</ymin>   <xmax>257</xmax>   <ymax>308</ymax>  </bndbox> </object> <object>  <name>traffic sign</name>  <bndbox>   <xmin>1258</xmin>   <ymin>33</ymin>   <xmax>1276</xmax>   <ymax>78</ymax>  </bndbox> </object> <object>  <name>car</name>  <bndbox>   <xmin>164</xmin>   <ymin>287</ymin>   <xmax>200</xmax>   <ymax>312</ymax>  </bndbox> </object> <object>  <name>car</name>  <bndbox>   <xmin>230</xmin>   <ymin>289</ymin>   <xmax>266</xmax>   <ymax>330</ymax>  </bndbox> </object></annotation>