<?xml version="1.0" encoding="utf-8"?><annotation> <filename>7b995f4e-81c9d093.jpg</filename> <object>  <name>car</name>  <bndbox>   <xmin>491</xmin>   <ymin>328</ymin>   <xmax>508</xmax>   <ymax>349</ymax>  </bndbox> </object> <object>  <name>car</name>  <bndbox>   <xmin>476</xmin>   <ymin>332</ymin>   <xmax>500</xmax>   <ymax>360</ymax>  </bndbox> </object> <object>  <name>car</name>  <bndbox>   <xmin>432</xmin>   <ymin>328</ymin>   <xmax>484</xmax>   <ymax>374</ymax>  </bndbox> </object> <object>  <name>car</name>  <bndbox>   <xmin>492</xmin>   <ymin>330</ymin>   <xmax>581</xmax>   <ymax>401</ymax>  </bndbox> </object></annotation>