<?xml version="1.0" encoding="utf-8"?><annotation> <filename>87b7ff1d-b143ba0f.jpg</filename> <object>  <name>traffic sign</name>  <bndbox>   <xmin>588</xmin>   <ymin>178</ymin>   <xmax>630</xmax>   <ymax>220</ymax>  </bndbox> </object> <object>  <name>car</name>  <bndbox>   <xmin>285</xmin>   <ymin>233</ymin>   <xmax>327</xmax>   <ymax>300</ymax>  </bndbox> </object> <object>  <name>car</name>  <bndbox>   <xmin>304</xmin>   <ymin>207</ymin>   <xmax>477</xmax>   <ymax>362</ymax>  </bndbox> </object> <object>  <name>bus</name>  <bndbox>   <xmin>684</xmin>   <ymin>0</ymin>   <xmax>1280</xmax>   <ymax>445</ymax>  </bndbox> </object></annotation>