<?xml version="1.0" encoding="utf-8"?><annotation> <filename>90b28b1b-8dc37e3c.jpg</filename> <object>  <name>traffic sign</name>  <bndbox>   <xmin>481</xmin>   <ymin>149</ymin>   <xmax>555</xmax>   <ymax>172</ymax>  </bndbox> </object> <object>  <name>traffic sign</name>  <bndbox>   <xmin>453</xmin>   <ymin>154</ymin>   <xmax>475</xmax>   <ymax>175</ymax>  </bndbox> </object> <object>  <name>traffic light</name>  <bndbox>   <xmin>491</xmin>   <ymin>187</ymin>   <xmax>498</xmax>   <ymax>197</ymax>  </bndbox> </object> <object>  <name>traffic light</name>  <bndbox>   <xmin>452</xmin>   <ymin>193</ymin>   <xmax>459</xmax>   <ymax>201</ymax>  </bndbox> </object> <object>  <name>traffic light</name>  <bndbox>   <xmin>408</xmin>   <ymin>193</ymin>   <xmax>414</xmax>   <ymax>207</ymax>  </bndbox> </object> <object>  <name>traffic light</name>  <bndbox>   <xmin>391</xmin>   <ymin>188</ymin>   <xmax>398</xmax>   <ymax>203</ymax>  </bndbox> </object> <object>  <name>car</name>  <bndbox>   <xmin>533</xmin>   <ymin>203</ymin>   <xmax>561</xmax>   <ymax>223</ymax>  </bndbox> </object> <object>  <name>car</name>  <bndbox>   <xmin>589</xmin>   <ymin>194</ymin>   <xmax>653</xmax>   <ymax>244</ymax>  </bndbox> </object> <object>  <name>car</name>  <bndbox>   <xmin>658</xmin>   <ymin>155</ymin>   <xmax>742</xmax>   <ymax>266</ymax>  </bndbox> </object> <object>  <name>car</name>  <bndbox>   <xmin>185</xmin>   <ymin>219</ymin>   <xmax>242</xmax>   <ymax>286</ymax>  </bndbox> </object> <object>  <name>car</name>  <bndbox>   <xmin>198</xmin>   <ymin>220</ymin>   <xmax>338</xmax>   <ymax>330</ymax>  </bndbox> </object> <object>  <name>car</name>  <bndbox>   <xmin>287</xmin>   <ymin>204</ymin>   <xmax>568</xmax>   <ymax>413</ymax>  </bndbox> </object> <object>  <name>car</name>  <bndbox>   <xmin>0</xmin>   <ymin>235</ymin>   <xmax>119</xmax>   <ymax>296</ymax>  </bndbox> </object> <object>  <name>car</name>  <bndbox>   <xmin>708</xmin>   <ymin>9</ymin>   <xmax>1279</xmax>   <ymax>470</ymax>  </bndbox> </object> <object>  <name>bus</name>  <bndbox>   <xmin>634</xmin>   <ymin>130</ymin>   <xmax>744</xmax>   <ymax>210</ymax>  </bndbox> </object></annotation>