<?xml version="1.0" encoding="utf-8"?><annotation> <filename>91c0fe97-042a178d.jpg</filename> <object>  <name>car</name>  <bndbox>   <xmin>19</xmin>   <ymin>290</ymin>   <xmax>325</xmax>   <ymax>406</ymax>  </bndbox> </object> <object>  <name>traffic light</name>  <bndbox>   <xmin>675</xmin>   <ymin>258</ymin>   <xmax>687</xmax>   <ymax>286</ymax>  </bndbox> </object> <object>  <name>traffic light</name>  <bndbox>   <xmin>776</xmin>   <ymin>267</ymin>   <xmax>799</xmax>   <ymax>299</ymax>  </bndbox> </object> <object>  <name>car</name>  <bndbox>   <xmin>326</xmin>   <ymin>286</ymin>   <xmax>477</xmax>   <ymax>383</ymax>  </bndbox> </object></annotation>