<?xml version="1.0" encoding="utf-8"?><annotation> <filename>92779fe7-42b44f68.jpg</filename> <object>  <name>car</name>  <bndbox>   <xmin>320</xmin>   <ymin>381</ymin>   <xmax>395</xmax>   <ymax>449</ymax>  </bndbox> </object> <object>  <name>car</name>  <bndbox>   <xmin>391</xmin>   <ymin>355</ymin>   <xmax>510</xmax>   <ymax>465</ymax>  </bndbox> </object> <object>  <name>car</name>  <bndbox>   <xmin>507</xmin>   <ymin>344</ymin>   <xmax>757</xmax>   <ymax>499</ymax>  </bndbox> </object> <object>  <name>car</name>  <bndbox>   <xmin>215</xmin>   <ymin>404</ymin>   <xmax>268</xmax>   <ymax>439</ymax>  </bndbox> </object> <object>  <name>car</name>  <bndbox>   <xmin>123</xmin>   <ymin>403</ymin>   <xmax>196</xmax>   <ymax>467</ymax>  </bndbox> </object> <object>  <name>car</name>  <bndbox>   <xmin>1</xmin>   <ymin>403</ymin>   <xmax>147</xmax>   <ymax>518</ymax>  </bndbox> </object> <object>  <name>car</name>  <bndbox>   <xmin>759</xmin>   <ymin>346</ymin>   <xmax>981</xmax>   <ymax>458</ymax>  </bndbox> </object></annotation>