<?xml version="1.0" encoding="utf-8"?><annotation> <filename>a5b6d9d0-6b4e063a.jpg</filename> <object>  <name>car</name>  <bndbox>   <xmin>145</xmin>   <ymin>126</ymin>   <xmax>988</xmax>   <ymax>616</ymax>  </bndbox> </object> <object>  <name>car</name>  <bndbox>   <xmin>52</xmin>   <ymin>310</ymin>   <xmax>221</xmax>   <ymax>423</ymax>  </bndbox> </object> <object>  <name>traffic sign</name>  <bndbox>   <xmin>750</xmin>   <ymin>89</ymin>   <xmax>795</xmax>   <ymax>189</ymax>  </bndbox> </object></annotation>