<?xml version="1.0" encoding="utf-8"?><annotation> <filename>acff5cdd-a61f38c2.jpg</filename> <object>  <name>car</name>  <bndbox>   <xmin>0</xmin>   <ymin>212</ymin>   <xmax>183</xmax>   <ymax>373</ymax>  </bndbox> </object> <object>  <name>car</name>  <bndbox>   <xmin>156</xmin>   <ymin>176</ymin>   <xmax>356</xmax>   <ymax>312</ymax>  </bndbox> </object> <object>  <name>car</name>  <bndbox>   <xmin>363</xmin>   <ymin>211</ymin>   <xmax>461</xmax>   <ymax>270</ymax>  </bndbox> </object> <object>  <name>car</name>  <bndbox>   <xmin>451</xmin>   <ymin>205</ymin>   <xmax>495</xmax>   <ymax>251</ymax>  </bndbox> </object> <object>  <name>car</name>  <bndbox>   <xmin>503</xmin>   <ymin>204</ymin>   <xmax>548</xmax>   <ymax>243</ymax>  </bndbox> </object></annotation>