<?xml version="1.0" encoding="utf-8"?><annotation> <filename>af263edb-56de3330.jpg</filename> <object>  <name>car</name>  <bndbox>   <xmin>236</xmin>   <ymin>332</ymin>   <xmax>360</xmax>   <ymax>390</ymax>  </bndbox> </object> <object>  <name>car</name>  <bndbox>   <xmin>831</xmin>   <ymin>348</ymin>   <xmax>888</xmax>   <ymax>376</ymax>  </bndbox> </object> <object>  <name>car</name>  <bndbox>   <xmin>938</xmin>   <ymin>341</ymin>   <xmax>1063</xmax>   <ymax>428</ymax>  </bndbox> </object> <object>  <name>car</name>  <bndbox>   <xmin>1026</xmin>   <ymin>267</ymin>   <xmax>1278</xmax>   <ymax>465</ymax>  </bndbox> </object> <object>  <name>traffic sign</name>  <bndbox>   <xmin>967</xmin>   <ymin>271</ymin>   <xmax>986</xmax>   <ymax>304</ymax>  </bndbox> </object> <object>  <name>traffic sign</name>  <bndbox>   <xmin>700</xmin>   <ymin>320</ymin>   <xmax>711</xmax>   <ymax>324</ymax>  </bndbox> </object> <object>  <name>car</name>  <bndbox>   <xmin>674</xmin>   <ymin>337</ymin>   <xmax>826</xmax>   <ymax>380</ymax>  </bndbox> </object> <object>  <name>car</name>  <bndbox>   <xmin>362</xmin>   <ymin>335</ymin>   <xmax>653</xmax>   <ymax>387</ymax>  </bndbox> </object> <object>  <name>car</name>  <bndbox>   <xmin>655</xmin>   <ymin>339</ymin>   <xmax>671</xmax>   <ymax>347</ymax>  </bndbox> </object> <object>  <name>traffic light</name>  <bndbox>   <xmin>692</xmin>   <ymin>321</ymin>   <xmax>697</xmax>   <ymax>325</ymax>  </bndbox> </object> <object>  <name>traffic light</name>  <bndbox>   <xmin>627</xmin>   <ymin>318</ymin>   <xmax>633</xmax>   <ymax>324</ymax>  </bndbox> </object> <object>  <name>car</name>  <bndbox>   <xmin>1154</xmin>   <ymin>366</ymin>   <xmax>1279</xmax>   <ymax>598</ymax>  </bndbox> </object></annotation>