<?xml version="1.0" encoding="utf-8"?><annotation> <filename>b569f76a-33d451fe.jpg</filename> <object>  <name>traffic sign</name>  <bndbox>   <xmin>835</xmin>   <ymin>227</ymin>   <xmax>868</xmax>   <ymax>262</ymax>  </bndbox> </object> <object>  <name>traffic sign</name>  <bndbox>   <xmin>776</xmin>   <ymin>227</ymin>   <xmax>821</xmax>   <ymax>260</ymax>  </bndbox> </object> <object>  <name>traffic sign</name>  <bndbox>   <xmin>776</xmin>   <ymin>100</ymin>   <xmax>876</xmax>   <ymax>173</ymax>  </bndbox> </object> <object>  <name>traffic sign</name>  <bndbox>   <xmin>188</xmin>   <ymin>190</ymin>   <xmax>245</xmax>   <ymax>211</ymax>  </bndbox> </object> <object>  <name>traffic sign</name>  <bndbox>   <xmin>186</xmin>   <ymin>142</ymin>   <xmax>248</xmax>   <ymax>190</ymax>  </bndbox> </object> <object>  <name>car</name>  <bndbox>   <xmin>431</xmin>   <ymin>258</ymin>   <xmax>456</xmax>   <ymax>277</ymax>  </bndbox> </object> <object>  <name>car</name>  <bndbox>   <xmin>116</xmin>   <ymin>237</ymin>   <xmax>150</xmax>   <ymax>257</ymax>  </bndbox> </object></annotation>