<?xml version="1.0" encoding="utf-8"?><annotation> <filename>bc7a7a1f-dbeb9406.jpg</filename> <object>  <name>traffic sign</name>  <bndbox>   <xmin>242</xmin>   <ymin>185</ymin>   <xmax>268</xmax>   <ymax>207</ymax>  </bndbox> </object> <object>  <name>traffic sign</name>  <bndbox>   <xmin>180</xmin>   <ymin>202</ymin>   <xmax>227</xmax>   <ymax>214</ymax>  </bndbox> </object> <object>  <name>traffic sign</name>  <bndbox>   <xmin>170</xmin>   <ymin>219</ymin>   <xmax>227</xmax>   <ymax>232</ymax>  </bndbox> </object> <object>  <name>traffic sign</name>  <bndbox>   <xmin>1054</xmin>   <ymin>197</ymin>   <xmax>1065</xmax>   <ymax>212</ymax>  </bndbox> </object> <object>  <name>traffic sign</name>  <bndbox>   <xmin>1046</xmin>   <ymin>247</ymin>   <xmax>1104</xmax>   <ymax>262</ymax>  </bndbox> </object> <object>  <name>traffic sign</name>  <bndbox>   <xmin>1053</xmin>   <ymin>267</ymin>   <xmax>1076</xmax>   <ymax>316</ymax>  </bndbox> </object> <object>  <name>traffic light</name>  <bndbox>   <xmin>180</xmin>   <ymin>260</ymin>   <xmax>220</xmax>   <ymax>291</ymax>  </bndbox> </object> <object>  <name>traffic light</name>  <bndbox>   <xmin>247</xmin>   <ymin>262</ymin>   <xmax>255</xmax>   <ymax>294</ymax>  </bndbox> </object> <object>  <name>traffic light</name>  <bndbox>   <xmin>1041</xmin>   <ymin>270</ymin>   <xmax>1051</xmax>   <ymax>296</ymax>  </bndbox> </object> <object>  <name>pedestrian</name>  <bndbox>   <xmin>1038</xmin>   <ymin>365</ymin>   <xmax>1094</xmax>   <ymax>477</ymax>  </bndbox> </object> <object>  <name>car</name>  <bndbox>   <xmin>732</xmin>   <ymin>356</ymin>   <xmax>852</xmax>   <ymax>451</ymax>  </bndbox> </object> <object>  <name>car</name>  <bndbox>   <xmin>474</xmin>   <ymin>376</ymin>   <xmax>586</xmax>   <ymax>455</ymax>  </bndbox> </object> <object>  <name>car</name>  <bndbox>   <xmin>661</xmin>   <ymin>365</ymin>   <xmax>680</xmax>   <ymax>380</ymax>  </bndbox> </object> <object>  <name>car</name>  <bndbox>   <xmin>690</xmin>   <ymin>361</ymin>   <xmax>703</xmax>   <ymax>371</ymax>  </bndbox> </object> <object>  <name>car</name>  <bndbox>   <xmin>691</xmin>   <ymin>354</ymin>   <xmax>706</xmax>   <ymax>361</ymax>  </bndbox> </object> <object>  <name>car</name>  <bndbox>   <xmin>349</xmin>   <ymin>373</ymin>   <xmax>396</xmax>   <ymax>398</ymax>  </bndbox> </object> <object>  <name>car</name>  <bndbox>   <xmin>0</xmin>   <ymin>366</ymin>   <xmax>17</xmax>   <ymax>396</ymax>  </bndbox> </object> <object>  <name>traffic light</name>  <bndbox>   <xmin>259</xmin>   <ymin>89</ymin>   <xmax>285</xmax>   <ymax>157</ymax>  </bndbox> </object></annotation>