<?xml version="1.0" encoding="utf-8"?><annotation> <filename>bef906fc-b88eb3a5.jpg</filename> <object>  <name>traffic sign</name>  <bndbox>   <xmin>858</xmin>   <ymin>98</ymin>   <xmax>907</xmax>   <ymax>118</ymax>  </bndbox> </object> <object>  <name>traffic sign</name>  <bndbox>   <xmin>729</xmin>   <ymin>114</ymin>   <xmax>906</xmax>   <ymax>202</ymax>  </bndbox> </object> <object>  <name>traffic sign</name>  <bndbox>   <xmin>827</xmin>   <ymin>235</ymin>   <xmax>865</xmax>   <ymax>282</ymax>  </bndbox> </object> <object>  <name>traffic sign</name>  <bndbox>   <xmin>849</xmin>   <ymin>280</ymin>   <xmax>867</xmax>   <ymax>295</ymax>  </bndbox> </object> <object>  <name>traffic sign</name>  <bndbox>   <xmin>661</xmin>   <ymin>277</ymin>   <xmax>675</xmax>   <ymax>291</ymax>  </bndbox> </object> <object>  <name>traffic sign</name>  <bndbox>   <xmin>755</xmin>   <ymin>263</ymin>   <xmax>775</xmax>   <ymax>274</ymax>  </bndbox> </object> <object>  <name>car</name>  <bndbox>   <xmin>727</xmin>   <ymin>289</ymin>   <xmax>797</xmax>   <ymax>347</ymax>  </bndbox> </object> <object>  <name>car</name>  <bndbox>   <xmin>800</xmin>   <ymin>300</ymin>   <xmax>835</xmax>   <ymax>330</ymax>  </bndbox> </object></annotation>