<?xml version="1.0" encoding="utf-8"?><annotation> <filename>c91da210-1252e4c6.jpg</filename> <object>  <name>traffic light</name>  <bndbox>   <xmin>239</xmin>   <ymin>27</ymin>   <xmax>263</xmax>   <ymax>83</ymax>  </bndbox> </object> <object>  <name>traffic light</name>  <bndbox>   <xmin>327</xmin>   <ymin>166</ymin>   <xmax>347</xmax>   <ymax>208</ymax>  </bndbox> </object> <object>  <name>traffic sign</name>  <bndbox>   <xmin>326</xmin>   <ymin>142</ymin>   <xmax>345</xmax>   <ymax>159</ymax>  </bndbox> </object> <object>  <name>traffic sign</name>  <bndbox>   <xmin>239</xmin>   <ymin>5</ymin>   <xmax>259</xmax>   <ymax>25</ymax>  </bndbox> </object></annotation>